[
  {
    "#": 1,
    "Month": "April-19",
    "Event Name": "India China Investment Forum, Powered by Khaitan & Co.",
    "Date": "29 April",
    "Venue": "Delhi"
  },
  {
    "#": 2,
    "Month": "May-19",
    "Event Name": "IVCA - PwC Masterclass on Structuring Aspects & Recent Updates",
    "Date": "30 May",
    "Venue": "Bangalore"
  },
  {
    "#": 3,
    "Month": "June -19",
    "Event Name": "IVCA - NDA Masterclass on Key Fund Terms and Legal Considerations",
    "Date": "13 June",
    "Venue": "Mumbai"
  },
  {
    "#": 4,
    "Month": "June -19",
    "Event Name": "IVCA - Khaitan Interactive Session on Navigating Through the End of a Fund",
    "Date": "27th June",
    "Venue": "Bangalore"
  },
  {
    "#": 5,
    "Month": "June -19",
    "Event Name": "3rd IVCA LP Summit",
    "Date": "5 July",
    "Venue": "Mumbai"
  },
  {
    "#": 5,
    "Month": "July - 20",
    "Event Name": "IVCA Delhi Circles",
    "Date": "24 July",
    "Venue": "Delhi"
  },
  {
    "#": 7,
    "Month": "August-19",
    "Event Name": "RE & Infra Council Meeting (Town Hall / Roundtable / Power Meet)",
    "Date": "1 Aug",
    "Venue": "Mumbai"
  },
  {
    "#": 8,
    "Month": "August-19",
    "Event Name": "IVCA Unbound",
    "Date": "9 Aug",
    "Venue": "Delhi"
  },
  {
    "#": 9,
    "Month": "August-19",
    "Event Name": "IVCA Unbound",
    "Date": "23 Aug",
    "Venue": "Mumbai"
  },
  {
    "#": 10,
    "Month": "August-19",
    "Event Name": "IVCA Unwind",
    "Date": "30 Aug",
    "Venue": "Bangalore"
  },
  {
    "#": 12,
    "Month": "September-19",
    "Event Name": "IVCA LP Training",
    "Date": "5 Sept",
    "Venue": "Mumbai"
  },
  {
    "#": 13,
    "Month": "September-19",
    "Event Name": "LP Training (contd..), EC Meeting &  IVCA Members Gathering",
    "Date": "6 Sept",
    "Venue": "Mumbai"
  },
  {
    "#": 14,
    "Month": "September-19",
    "Event Name": "IVCA Unwind",
    "Date": "13 Sept",
    "Venue": "Mumbai"
  },
  {
    "#": 16,
    "Month": "September-19",
    "Event Name": "IVCA Unwind",
    "Date": "27 Sept",
    "Venue": "Delhi"
  },
  {
    "#": 15,
    "Month": "October-19",
    "Event Name": "IVCA Unbound",
    "Date": "18th Oct",
    "Venue": "Bangalore"
  },
  {
    "#": 17,
    "Month": "November-19",
    "Event Name": "IVCA Unplug - Golf League",
    "Date": "1 Nov",
    "Venue": "Delhi"
  },
  {
    "#": 18,
    "Month": "November-19",
    "Event Name": "IVCA VC Meet at Nasscom Product Conclave",
    "Date": "5-6 Nov",
    "Venue": "Bangalore"
  },
  {
    "#": 19,
    "Month": "November-19",
    "Event Name": "IVCA Unplug",
    "Date": "15 Nov",
    "Venue": "Mumbai"
  },
  {
    "#": 20,
    "Month": "November-19",
    "Event Name": "IVCA Unplug",
    "Date": "29 Nov",
    "Venue": "Bangalore"
  },
  {
    "#": 21,
    "Month": "December-19",
    "Event Name": "Empea Masterclass",
    "Date": "3 Dec",
    "Venue": "Mumbai"
  },
  {
    "#": 22,
    "Month": "December-19",
    "Event Name": "IVCA & Quadria Capital's India Healthcare Leadreship Summit",
    "Date": "4 Dec",
    "Venue": "Mumbai"
  },
  {
    "#": 23,
    "Month": "January-20",
    "Event Name": "IVCA Conclave 9th Edition",
    "Date": "30-31 Jan",
    "Venue": "Delhi"
  }
]
